{
  "income": [
    {
      "type": "収入",
      "category": "Stripe入金",
      "reason": "クライアントからの支払い",
      "date": "2026-01-08",
      "from": "\"service-jp@paypal.com\" <service-jp@paypal.com>",
      "subject": "XMIND LTD様から￥90,000 JPYのお支払いがありました",
      "amount": "86270",
      "currency": "JPY",
      "attachments": "",
      "drive_urls": "",
      "msg_id": "19ba1b2d945449ba"
    },
    {
      "type": "収入",
      "category": "案件受注",
      "reason": "Readdy AI動画作成案件の支払い",
      "date": "2026-01-08",
      "from": "\"市岡直人\" <jiuhuot10@gmail.com>",
      "subject": "Re: 11月　Readdy AI動画作成(175-202511-01-006)ainote150000【重要】請求書発行に関するご案内",
      "amount": "70000",
      "currency": "JPY",
      "attachments": "",
      "drive_urls": "",
      "msg_id": "19b99cb9b6c9e2da"
    },
    {
      "type": "収入",
      "category": "案件受注",
      "reason": "ClimbBeyond案件の請求書",
      "date": "2026-01-05",
      "from": "Stripe <notifications@stripe.com>",
      "subject": "ClimbBeyonの適格請求書のお知らせ",
      "amount": "",
      "currency": "",
      "attachments": "",
      "drive_urls": "",
      "msg_id": "19b8edb77b798e2d"
    }
  ],
  "expenses": [
    {
      "category": "AI/SaaS",
      "project": "",
      "date": "2026-02-04",
      "from": "\"MainFunc PTE. LTD.\" <invoice+statements+acct_1Q2SePHy7UpDvrVi@stripe.com>",
      "subject": "MainFunc PTE. LTD. からの領収書 (領収書番号 2458-4720)",
      "amount": "314",
      "currency": "JPY",
      "attachments": "Invoice-F3B6E672-0011.pdf, Receipt-2458-4720.pdf",
      "drive_urls": "https://drive.google.com/file/d/1ofeasiXEIq38ISD7LaxLdlQnifMMH9Ta/view?usp=drivesdk\nhttps://drive.google.com/file/d/1RsPt8QQxzCsRJgBm9ZXXTeDry0yR0oaP/view?usp=drivesdk",
      "msg_id": "19c2ad75c81b7a14"
    },
    {
      "category": "X広告",
      "project": "AirCle/マーケ",
      "date": "2026-02-04",
      "from": "X <invoice+statements+acct_1Ika5JA3KZ32dPo1@stripe.com>",
      "subject": "Your receipt from X #2255-6359-5677",
      "amount": "918",
      "currency": "JPY",
      "attachments": "Invoice-ZKMCF8WO-0008.pdf, Receipt-2255-6359-5677.pdf",
      "drive_urls": "https://drive.google.com/file/d/19rSXGIyG2jMfHIjrZSn6WFf43EHKbI6Z/view?usp=drivesdk\nhttps://drive.google.com/file/d/1W5KH5sxuMdybtEWD7tUOwcunlvtu3TZA/view?usp=drivesdk",
      "msg_id": "19c269ebaf81b0d0"
    },
    {
      "category": "その他",
      "project": "",
      "date": "2026-02-02",
      "from": "\"植田 美香（Chatwork アシスタント）\" <news@ns.chatwork.com>",
      "subject": "【経理業務まるごと】リモートバックオフィスにおまかせ！",
      "amount": "",
      "currency": "",
      "attachments": "",
      "drive_urls": "",
      "msg_id": "19c20ad31f6c7d7e"
    },
    {
      "category": "X広告",
      "project": "AirCle/マーケ",
      "date": "2026-02-01",
      "from": "X <invoice+statements+acct_1Ika5JA3KZ32dPo1@stripe.com>",
      "subject": "Your receipt from X #2954-8844-6226",
      "amount": "918",
      "currency": "JPY",
      "attachments": "Invoice-8ANKTV9U-0003.pdf, Receipt-2954-8844-6226.pdf",
      "drive_urls": "https://drive.google.com/file/d/1NPIGQP0ZxFcjOn98CBZfw0I6IEEqM1ex/view?usp=drivesdk\nhttps://drive.google.com/file/d/1XVvtL-3tMEwIqZASCRufJk1MEKOASm3V/view?usp=drivesdk",
      "msg_id": "19c18009c7063acf"
    },
    {
      "category": "AI/SaaS",
      "project": "AirCle",
      "date": "2026-01-30",
      "from": "studio veco <invoice+statements+acct_1MnjcQG207ugzMIr@stripe.com>",
      "subject": "studio veco からの領収書 (領収書番号 2621-1000)",
      "amount": "5000",
      "currency": "JPY",
      "attachments": "Invoice-EYTSOGYB-0003.pdf, Receipt-2621-1000.pdf",
      "drive_urls": "https://drive.google.com/file/d/1ZYHmwQVlmWnwkBrVNHf_9EIYwLjHn9a_/view?usp=drivesdk\nhttps://drive.google.com/file/d/1py2zpKwaSiO_uqKnYsDyUJioNM6o_KtG/view?usp=drivesdk",
      "msg_id": "19c0e39ac3543f49"
    },
    {
      "category": "交通費",
      "project": "移動",
      "date": "2026-01-28",
      "from": "\"Trip.com\" <jp_flt_noreply@trip.com>",
      "subject": "お支払いが完了しました",
      "amount": "54754",
      "currency": "JPY",
      "attachments": "",
      "drive_urls": "",
      "msg_id": "19c04966d9f0e3d0"
    },
    {
      "category": "振込手数料",
      "project": "",
      "date": "2026-01-28",
      "from": "\"西日本シティ銀行\" <info01900007@webcenter.anser.or.jp>",
      "subject": "【西日本シティ銀行】振込依頼処理完了のお知らせ",
      "amount": "3",
      "currency": "JPY",
      "attachments": "",
      "drive_urls": "",
      "msg_id": "19c03afe9e0eba47"
    },
    {
      "category": "振込手数料",
      "project": "",
      "date": "2026-01-28",
      "from": "\"西日本シティ銀行\" <info01900007@webcenter.anser.or.jp>",
      "subject": "【西日本シティ銀行】振込依頼処理完了のお知らせ",
      "amount": "86",
      "currency": "JPY",
      "attachments": "",
      "drive_urls": "",
      "msg_id": "19c03afe9dffd936"
    },
    {
      "category": "振込手数料",
      "project": "",
      "date": "2026-01-28",
      "from": "\"西日本シティ銀行\" <info01900007@webcenter.anser.or.jp>",
      "subject": "【西日本シティ銀行】振込依頼処理完了のお知らせ",
      "amount": "217",
      "currency": "JPY",
      "attachments": "",
      "drive_urls": "",
      "msg_id": "19c03a40f3eee1b2"
    },
    {
      "category": "その他",
      "project": "",
      "date": "2026-01-27",
      "from": "Apple Store <applefukuoka@email.apple.com>",
      "subject": "Apple 福岡からの領収書です",
      "amount": "",
      "currency": "",
      "attachments": "EmailReceipt_20260127R0481215418_ja_JP.pdf",
      "drive_urls": "https://drive.google.com/file/d/1xlABnABafBBl1G_BLu-lP7jMZt_QB95P/view?usp=drivesdk",
      "msg_id": "19bfdb39e3970d0b"
    },
    {
      "category": "振込手数料",
      "project": "",
      "date": "2026-01-26",
      "from": "\"西日本シティ銀行\" <info01900007@webcenter.anser.or.jp>",
      "subject": "【西日本シティ銀行】振込依頼処理完了のお知らせ",
      "amount": "28",
      "currency": "JPY",
      "attachments": "",
      "drive_urls": "",
      "msg_id": "19bf7be62611498d"
    },
    {
      "category": "振込手数料",
      "project": "",
      "date": "2026-01-26",
      "from": "\"西日本シティ銀行\" <info01900007@webcenter.anser.or.jp>",
      "subject": "【西日本シティ銀行】振込依頼処理完了のお知らせ",
      "amount": "10",
      "currency": "JPY",
      "attachments": "",
      "drive_urls": "",
      "msg_id": "19bf7be5e70f472d"
    },
    {
      "category": "AI/SaaS",
      "project": "AirCle",
      "date": "2026-01-16",
      "from": "Aqua Voice <invoice+statements+acct_1OnZwWBmfy315IEC@stripe.com>",
      "subject": "Aqua Voice からの領収書 (領収書番号 2569-4866)",
      "amount": "9",
      "currency": "USD",
      "attachments": "Invoice-SXT4Z1LN-0003.pdf, Receipt-2569-4866.pdf",
      "drive_urls": "https://drive.google.com/file/d/1glkGAwYrJNOBmtq9a-T23YCVaVQu5Bxz/view?usp=drivesdk\nhttps://drive.google.com/file/d/1IDtHk2N9dTmC9BVxxF_XKKqObQm8gpmD/view?usp=drivesdk",
      "msg_id": "19bc4f05f47f1de9"
    },
    {
      "category": "AI/SaaS",
      "project": "",
      "date": "2026-01-10",
      "from": "Paddle <help@paddle.com>",
      "subject": "iMobie Inc. の領収書",
      "amount": "6468",
      "currency": "JPY",
      "attachments": "invoice_5306-25617_iMobie-Inc-.pdf",
      "drive_urls": "https://drive.google.com/file/d/1NIZum4CAvRSK0XQQOpm_mbWXWsWwQbff/view?usp=drivesdk",
      "msg_id": "19ba726665ea1ef9"
    },
    {
      "category": "AI/SaaS",
      "project": "AirCle",
      "date": "2026-01-08",
      "from": "Canva <no-reply@account.canva.com>",
      "subject": "Canvaよりご請求内容のお知らせ",
      "amount": "8300",
      "currency": "JPY",
      "attachments": "",
      "drive_urls": "",
      "msg_id": "19b9af14cf84be06"
    },
    {
      "category": "振込手数料",
      "project": "",
      "date": "2026-01-07",
      "from": "\"西日本シティ銀行\" <info01900007@webcenter.anser.or.jp>",
      "subject": "【西日本シティ銀行】振込依頼処理完了のお知らせ",
      "amount": "29",
      "currency": "JPY",
      "attachments": "",
      "drive_urls": "",
      "msg_id": "19b97f09ceb649ed"
    },
    {
      "category": "振込手数料",
      "project": "",
      "date": "2026-01-07",
      "from": "\"西日本シティ銀行\" <info01900007@webcenter.anser.or.jp>",
      "subject": "【西日本シティ銀行】振込依頼処理完了のお知らせ",
      "amount": "227",
      "currency": "JPY",
      "attachments": "",
      "drive_urls": "",
      "msg_id": "19b978689de0954d"
    },
    {
      "category": "振込手数料",
      "project": "",
      "date": "2026-01-07",
      "from": "\"西日本シティ銀行\" <info01900007@webcenter.anser.or.jp>",
      "subject": "【西日本シティ銀行】振込依頼処理完了のお知らせ",
      "amount": "199",
      "currency": "JPY",
      "attachments": "",
      "drive_urls": "",
      "msg_id": "19b978662fdbdb59"
    },
    {
      "category": "振込手数料",
      "project": "",
      "date": "2026-01-07",
      "from": "\"西日本シティ銀行\" <info01900007@webcenter.anser.or.jp>",
      "subject": "【西日本シティ銀行】振込依頼処理完了のお知らせ",
      "amount": "35",
      "currency": "JPY",
      "attachments": "",
      "drive_urls": "",
      "msg_id": "19b97866295613ab"
    },
    {
      "category": "事務所",
      "project": "AirCle",
      "date": "2026-01-07",
      "from": "\"市岡直人\" <jiuhuot10@gmail.com>",
      "subject": "Re: バーチャルオフィスプランご請求のご案内【バーチャルオフィス スタートアップ】",
      "amount": "12100",
      "currency": "JPY",
      "attachments": "",
      "drive_urls": "",
      "msg_id": "19b9747541cb0fdd"
    },
    {
      "category": "AI/SaaS",
      "project": "AirCle",
      "date": "2026-01-07",
      "from": "studio veco <invoice+statements+acct_1MnjcQG207ugzMIr@stripe.com>",
      "subject": "studio veco からの領収書 (領収書番号 2600-0795)",
      "amount": "5000",
      "currency": "JPY",
      "attachments": "Invoice-EYTSOGYB-0002.pdf, Receipt-2600-0795.pdf",
      "drive_urls": "https://drive.google.com/file/d/10Ul6gbkKyEHtzJQefVDNEl7SRGu7ugME/view?usp=drivesdk\nhttps://drive.google.com/file/d/1CrFBhkYDf7UbphWZq8GtHC1cxkRODwTn/view?usp=drivesdk",
      "msg_id": "19b96aa5825694dd"
    },
    {
      "category": "X広告",
      "project": "AirCle/マーケ",
      "date": "2026-01-04",
      "from": "X <invoice+statements+acct_1Ika5JA3KZ32dPo1@stripe.com>",
      "subject": "Your receipt from X #2675-8080-6924",
      "amount": "918",
      "currency": "JPY",
      "attachments": "Invoice-ZKMCF8WO-0007.pdf, Receipt-2675-8080-6924.pdf",
      "drive_urls": "https://drive.google.com/file/d/1JfEvGsbK4i4e9zF3kGfw_eqmXw9LhVgQ/view?usp=drivesdk\nhttps://drive.google.com/file/d/1GVCGHMO87UVOuhJ3Ob9aXvadxKhPc80B/view?usp=drivesdk",
      "msg_id": "19b86f72589c193b"
    },
    {
      "category": "X広告",
      "project": "AirCle/マーケ",
      "date": "2026-01-01",
      "from": "X <invoice+statements+acct_1Ika5JA3KZ32dPo1@stripe.com>",
      "subject": "Your receipt from X #2320-4152-4342",
      "amount": "918",
      "currency": "JPY",
      "attachments": "Invoice-8ANKTV9U-0002.pdf, Receipt-2320-4152-4342.pdf",
      "drive_urls": "https://drive.google.com/file/d/1R8yE79nCldaIu9oSaWJ0eyRO5Xd5aJAL/view?usp=drivesdk\nhttps://drive.google.com/file/d/1_v0Lf9AMDqp02Cfo6w6j99Kw6HPHHX5s/view?usp=drivesdk",
      "msg_id": "19b7854f1e815408"
    }
  ],
  "noise": [
    {
      "reason": "予約確認（支払い別途）",
      "date": "2026-01-28",
      "from": "\"Trip.com\" <jp_flt_noreply@trip.com>",
      "subject": "航空券予約確認書： 東京 - ロサンゼルス",
      "amount": "",
      "currency": "",
      "attachments": "旅程表（eチケットお客様控え）.pdf, 電子領収書.pdf",
      "drive_urls": "https://drive.google.com/file/d/177u3TTkyD-U1iXSXkf63mY4ATAP1GDDE/view?usp=drivesdk\nhttps://drive.google.com/file/d/1A3Fjn4Nyz0isdt4hJbUgCYdyVNyH2xn4/view?usp=drivesdk",
      "msg_id": "19c0499e3038e44f"
    },
    {
      "reason": "決済失敗",
      "date": "2026-01-28",
      "from": "\"Trip.com\" <jp_flt_noreply@trip.com>",
      "subject": "お支払いに失敗しました",
      "amount": "54840",
      "currency": "JPY",
      "attachments": "",
      "drive_urls": "",
      "msg_id": "19c0495d3e8db0cf"
    },
    {
      "reason": "決済失敗",
      "date": "2026-01-28",
      "from": "\"Trip.com\" <jp_flt_noreply@trip.com>",
      "subject": "お支払いに失敗しました",
      "amount": "54840",
      "currency": "JPY",
      "attachments": "",
      "drive_urls": "",
      "msg_id": "19c0494b56713eb7"
    },
    {
      "reason": "広告メール",
      "date": "2026-01-27",
      "from": "\"桜井祐実（株式会社kubell）\" <news@ns.chatwork.com>",
      "subject": "月末の支払いがピンチ？！緊急時のあなたを救う資金調達手段とは？",
      "amount": "",
      "currency": "",
      "attachments": "",
      "drive_urls": "",
      "msg_id": "19bfea4f2ae8c271"
    },
    {
      "reason": "広告メール",
      "date": "2026-01-26",
      "from": "\"ヤマダデンキ \" <noreply@tpgaw.jp>",
      "subject": "ヤマダデンキでのお買い物なら便利でお得なヤマダPayがおすすめ！",
      "amount": "",
      "currency": "",
      "attachments": "",
      "drive_urls": "",
      "msg_id": "19bf8c028ab712e5"
    },
    {
      "reason": "広告メール",
      "date": "2026-01-21",
      "from": "\"植田美香（Chatwork）\" <news@ns.chatwork.com>",
      "subject": "【銀行融資が通らない？】それ、むしろチャンスです",
      "amount": "",
      "currency": "",
      "attachments": "",
      "drive_urls": "",
      "msg_id": "19be2e89e4e8ec8a"
    },
    {
      "reason": "セキュリティ通知",
      "date": "2026-01-07",
      "from": "\"service-jp@paypal.com\" <service-jp@paypal.com>",
      "subject": "この信頼できる端末のログイン状態を維持する ",
      "amount": "",
      "currency": "",
      "attachments": "",
      "drive_urls": "",
      "msg_id": "19b9c6998635f652"
    },
    {
      "reason": "契約締結",
      "date": "2026-01-05",
      "from": "\"freeeサイン事務局\" <notice@ninja-sign.com>",
      "subject": "株式会社LEC 本田直久 様から送信されたマーケティング講座契約書の署名・合意をしました",
      "amount": "",
      "currency": "",
      "attachments": "",
      "drive_urls": "",
      "msg_id": "19b8b9da2db1a193"
    },
    {
      "reason": "アカウント設定",
      "date": "2026-01-02",
      "from": "\"service-jp@paypal.com\" <service-jp@paypal.com>",
      "subject": "銀行口座を登録しました",
      "amount": "",
      "currency": "",
      "attachments": "",
      "drive_urls": "",
      "msg_id": "19b7dc065d2a420c"
    }
  ],
  "summary": {
    "total_income_jpy": 156270,
    "total_expense_jpy": 96442,
    "total_expense_usd": 9
  }
}